{
  "music": {
    "track": "chase_1",
    "volume": 0.25
  },

  "graphics": {
    "color_id": 1,

    "filter_enabled": true,
    "filter_brightness": -32,

    "spotlight_enabled": true
  },

  "initial_condition": {
    "position": [1570, 590],
    "angle": 90
  },

  "detectors": {
    "next_zone_1": {
      "rect": [0, 144, 25, 240],
      "action": "switch_zone",
      "map_name": "level_9",
      "player_new_position": [1570, 192],
      "player_new_angle": 90
    }
  },

  "entities": {
  }
}
