{
  "music": {
    "track": "chase_2",
    "volume": 0.75
  },

  "graphics": {
    "color_id": 1,

    "filter_enabled": true,
    "filter_brightness": -32,

    "spotlight_enabled": true
  },

  "initial_condition": {
    "position": [1570, 645],
    "angle": 0
  },

  "detectors": {
    "next_zone_1": {
      "rect": [1575, 200, 25, 300],
      "action": "switch_zone",
      "map_name": "level_6",
      "player_new_position": [50, 616],
      "player_new_angle": 90
    }
  },

  "entities": {
    "bloby": {
      "type": "blob",
      "position": 0,
      "speed": 50,
      "direction": [1, 0]
    }
  }
}
